{
  "posts": [
    {
      "id": 1,
      "title": "test페이지가 오픈되었어요",
      "username": "관리자",
      "content": "내용1",
      "createdAt": "2022-01-03"
    },
    {
      "id": 2,
      "title": "json-server test~",
      "username": "김말이",
      "content": "내용2",
      "createdAt": "2022-01-03"
    },
    {
      "id": 3,
      "title": "세번째 새글",
      "username": "떡말이",
      "content": "내용3",
      "createdAt": "2022-01-03"
    },
    {
      "id": 4,
      "title": "네번째 새글",
      "username": "계란말이",
      "content": "내용4",
      "createdAt": "2022-01-03"
    }
  ]
}